README.md
setup.py
lightbringer/__init__.py
lightbringer/_compat.py
lightbringer/connection.py
lightbringer/reader.py
lightbringer/writer.py
lightbringer.egg-info/PKG-INFO
lightbringer.egg-info/SOURCES.txt
lightbringer.egg-info/dependency_links.txt
lightbringer.egg-info/requires.txt
lightbringer.egg-info/top_level.txt