Metadata-Version: 1.1
Name: lightbringer
Version: 0.0.1
Summary: Modern, simple and robust asyncio NSQ client library
Home-page: http://git.glose.com/opensource/lightbringer
Author: Glose
Author-email: hello+lightbringer@glose.com
License: MIT
Platform: UNKNOWN
Classifier: Development Status :: 4 - Beta
Classifier: Intended Audience :: Developers
Classifier: License :: OSI Approved :: MIT License
Classifier: Operating System :: OS Independent
Classifier: Programming Language :: Python
Classifier: Programming Language :: Python :: 3.6
Classifier: Programming Language :: Python :: 3.7
Classifier: Topic :: Software Development :: Libraries :: Python Modules
